LICENSE.txt
MANIFEST.in
README.md
README.rst
requirements.txt
setup.py
demo/__init__.py
demo/demo.py
pdbsync/__init__.py
pdbsync/console_scripts.py
pdbsync/logo.txt
pdbsync.egg-info/PKG-INFO
pdbsync.egg-info/SOURCES.txt
pdbsync.egg-info/dependency_links.txt
pdbsync.egg-info/entry_points.txt
pdbsync.egg-info/top_level.txt
pdbsync/cli/__init__.py
pdbsync/cli/config_parser.py
pdbsync/cli/log.py
pdbsync/cli/logo.py
pdbsync/core/__init__.py
pdbsync/core/constants.py
pdbsync/core/lib.py
pdbsync/core/sync.py
pdbsync/core/plugins/__init__.py
pdbsync/core/plugins/db_create.py
pdbsync/core/plugins/dump.py
pdbsync/core/plugins/execute.py
pdbsync/test/__init__.py